{"Tocca.js": "0.1.21", "parsley.js": "2.0.7", "angular-md5": "0.1.7", "URI.js": "1.15.1", "knockout-validation": "2.0.2", "knockout": "3.3.0", "6px": "1.0.3", "quicksound.js": "0.5.2", "html5sortable": "0.2.4", "aegis": "1.3.3", "beepjs": "0.0.1", "js-data-angular": "3.0.0-beta.2", "gmaps4rails": "2.1.2", "jquery-sidebar": "3.2.0", "globalize": "1.0.0-alpha.21", "masonry": "3.3.0", "16pixels": "0.1.5", "skeleton": "2.0.4", "jquery.wookmark": "1.3.1", "chainloading": "1.1.0", "bootstrap-table": "1.7.0", "aui": "5.6.10", "ng-tags-input": "2.3.0", "cytoscape": "2.3.16", "underscore.js": "1.8.3", "chrome-frame": "1.0.3", "primish": "0.3.9", "css3pie": "2.0beta1", "opal-jquery": "0.0.8", "protovis": "3.3.1", "bower-angular-translate": "2.7.0", "icono": "1.3.0", "awesome-bootstrap-checkbox": "v0.2.3", "immutable": "3.7.2", "jquery.html5loader": "1.8.0", "ember-resource.js": "2.0.0", "pivottable": "1.4.0", "jasny-bootstrap": "3.1.3", "xuijs": "2.3.2", "twemoji": "1.4.1", "odometer.js": "0.4.6", "require.js": "2.1.17", "angular-strap": "2.2.1", "morris.js": "0.5.1", "jquery.blockUI": "2.66.0-2013.10.09", "radio": "0.2.0", "mobilizejs": "0.9", "twix.js": "0.3.0", "jquery.perfect-scrollbar": "0.5.9", "trunk8": "1.3.3", "eventable": "1.0.4", "jquery.lifestream": "0.3.7", "garlic.js": "1.2.2", "angular-formly-templates-bootstrap": "4.0.9", "condition": "1.2.0", "jquery-twinkle": "0.8.0", "materialize": "0.96.1", "simple-text-rotator": "1.0.0", "basics": "1.2.2", "magic": "1.1.0", "jqgrid": "4.6.0", "deck.js": "1.1.0", "favico.js": "0.3.7", "basis.js": "1.3.3", "bootstrap-colorpicker": "2.1.1", "jquery.meiomask": "1.1.14", "jquery.textcomplete": "0.2.2", "angular-autofields": "2.1.8", "stellar.js": "0.6.2", "emberFire": "1.0.9", "sockjs-client": "0.3.4", "nprogress": "0.1.6", "ng-table": "0.3.3", "motajs": "0.6.4", "localforage": "1.2.2", "i3d3": "0.9.1", "angular-moment": "0.10.1", "metisMenu": "2.0.0", "fabric.js": "1.5.0", "packery": "1.4.1", "angular-formly": "6.4.0-beta.4", "stapes": "0.8.1", "rxjs-dom": "2.0.7", "angular-spinner": "0.6.1", "fiber": "1.0.5", "Faker": "0.7.2", "bootstrap-lightbox": "0.7.0", "randomcolor": "0.1.1", "m8tro-bootstrap": "3.3.4", "chartist": "0.7.4", "webfont": "1.5.18", "quill": "0.19.11", "backbone.eventbinder": "0.1.0", "ol3": "3.5.0", "backbone.layoutmanager": "0.9.7", "hopscotch": "0.2.4", "eve.js": "0.8.4", "bitcoinjs-lib": "0.2.0-1", "seedrandom": "2.4.0", "blanket.js": "1.1.4", "jquery.transit": "0.9.12", "jquery-hashchange": "v1.3", "jquery-fracs": "0.15.1", "jxon": "1.3.2", "jquery-idletimer": "1.0.0", "photoswipe": "3.0.5", "jquery.cycle": "3.03", "accounting.js": "0.4.1", "angular-azure-mobile-service": "1.3.8", "jquery.collapsible": "1.2", "jquery.ba-bbq": "1.2.1", "mathjax": "2.5.3", "processing.js": "1.4.8", "superagent": "0.15.7", "klass": "1.4.0", "weather-icons": "1.3.2", "fuse.js": "1.2.2", "lazysizes": "1.1.0-rc3", "crunch": "1.0.3", "purl": "2.3.1", "typescript": "1.0.0", "linq.js": "2.2.0.2", "quo.js": "2.3.6", "sinon.js": "1.7.3", "postscribe": "1.4.0", "jquery-nivoslider": "3.2", "jasmine": "2.3.1", "devicons": "1.8.0", "keymaster": "1.6.1", "ifvisible": "1.0.1", "jQuery.mmenu": "5.1.2", "midi.js": "0.3.0", "velocity": "1.2.2", "sigma.js": "1.0.3", "reactive-coffee": "1.2.2", "wavesurfer.js": "0.1.7", "epitome": "0.3.0", "angular-ui-router": "0.2.14", "js-data-http": "2.0.0-beta.3", "scaleapp": "0.4.3", "yamlcss": "4.1.2", "require-text": "2.0.12", "slidebars": "0.10.2", "history.js": "1.8", "sweetalert": "0.5.0", "knockout-paging": "0.1.0", "xively-js": "1.0.4", "tweenjs": "0.6.0", "ember-localstorage-adapter": "0.3.1", "omniscient": "3.1.0", "knockout-postbox": "0.5.1", "moment-timezone": "0.3.1", "camanjs": "4.1.2", "ractive.js": "0.3.7", "d3-tip": "0.6.3", "easy-pie-chart": "2.1.4", "Hoverizr": "1.0", "tweet": "2.2.0", "picturefill": "2.3.1", "hallo.js": "1.1.1", "jquery-mobile-datebox": "1.1.1", "bootstrap3-dialog": "1.34.4", "rivets": "0.8.1", "polymer": "0.5.5-rc1", "libil": "0.1.2", "backbone-super": "1.0.2", "p5.js": "0.4.4", "marked": "0.3.2", "stupidtable": "0.0.1", "jquery-searcher": "0.2.0", "json5": "0.3.0", "Vague.js": "0.0.6", "json3": "3.3.2", "json2": "20140204", "metrics-graphics": "2.4.0", "document-register-element": "0.3.0", "jstree": "3.1.1", "EaselJS": "0.8.0", "avgrund": "0.1.0", "taskforce": "1.0", "jquery-tools": "1.2.7", "sammy.js": "0.7.6", "cookiejar": "0.5.1", "jcarousel": "0.3.3", "jquery.nanoscroller": "0.8.7", "bootstrap-validator": "0.4.5", "twig.js": "0.6.0", "pubnub": "3.7.7", "signature_pad": "1.3.6", "jinplace": "1.1.0", "oauth-io": "0.9.0", "mori": "0.3.2", "localStorage": "2.0.1", "mathjs": "1.6.0", "angular-translate-storage-cookie": "2.7.0", "textAngular": "1.3.11", "slabText": "2.3", "js-sequence-diagrams": "1.0.4", "Chart.js": "1.0.2", "galleria": "1.4.2", "qunit": "1.16.0", "pleasejs": "0.2.0", "lunr.js": "0.5.9", "gl-matrix": "2.2.1", "angular-file-upload": "1.1.5", "backbone-react-component": "0.8.1", "benchmark": "1.0.0", "bootstrap-tokenfield": "0.12.0", "Colors.js": "1.2.4", "jquery.gridster": "0.5.6", "jsPlumb": "1.4.1", "sprintf": "1.0.2", "mustache.js": "0.8.1", "luminateExtend": "1.7.0", "backbone-relational": "0.9.0", "bespoke.js": "1.0.0-beta.2", "svg.connectable.js": "1.0.1", "jQuery.BlackAndWhite": "0.3.7", "kronos.js": "0.7.2", "sketch.js": "1.0.0", "prism": "0.0.1", "floatlabels.js": "1.0.0", "ramda": "0.13.0", "F2": "1.4.0", "fastclick": "1.0.6", "ui-selectableScroll": "0.1.4", "Readmore.js": "2.0.5", "mo": "1.7.3", "leaflet-dvf": "0.2", "jquery.caroufredsel": "6.2.1", "selectize.js": "0.12.1", "angular-material-icons": "0.4.0", "jquery-mockjax": "1.6.2", "screenfull.js": "2.0.0", "jquery-timepicker": "1.6.11", "aight": "1.2.2", "ractive-require": "0.2.0", "jquery.devbridge-autocomplete": "1.2.7", "jquery.allowed-chars": "1.0.4", "jquery.easytabs": "3.2.0", "money.js": "0.1.3", "shine.js": "0.2.7", "jquery-smooth-scroll": "1.5.5", "jquery.businessHours": "1.0.1", "flipCounter": "1.2", "datatables-fixedheader": "2.1.1", "swfobject": "2.2", "jquery-smoove": "0.2.7", "list.js": "1.1.1", "jsSHA": "1.42", "gorillascript": "0.9.10", "oj.GitHubButton": "latest", "drawer": "2.4.0", "webtorrent": "0.30.0", "animsition": "3.5.1", "rangy": "1.2.3", "webicons": "2.0.0", "ocanvas": "2.7.3", "snap.svg": "0.3.0", "foundicons": "3.0.0", "cubism": "1.6.0", "spf": "2.2.0", "mootools-more": "1.5.1", "normalize": "3.0.3", "galleriffic": "2.0.1", "arbor": "0.91.0", "oj.YouTubeVideo": "latest", "urljs": "1.1.0", "angular.js": "1.4.0-rc.1", "bootstrap-modal": "2.2.5", "jquery-contextify": "1.0.5", "jqueryui-touch-punch": "0.2.3", "move.js": "0.4.0", "stroll.js": "1.0", "fluidbox": "1.4.3.1", "responsive-nav.js": "1.12", "pure": "0.6.0", "expect.js": "0.2.0", "jquery.appear": "0.3.3", "webuploader": "0.1.1", "hydna": "1.0.1", "bonsai": "0.4.5", "jquery.scroll4ever": "1.0.0", "scion": "0.0.3", "watch": "2.0.3", "casualjs": "0.1.2", "jschannel": "1.0.0-git-commit1-8c4f7eb", "space": "0.8.4", "jquery.hoverintent": "2013.03.11", "jquery-prompt21": "1.1.1", "jquery-instagram": "0.3.1", "backbone.modelbinder": "1.0.5", "js-data-localstorage": "2.0.0-beta.4", "paypaljsbuttons": "1.0.2", "html-inspector": "0.8.2", "notifxi": "0.2.2", "jquery-customSelect": "0.4.1", "hasher": "1.2.0", "amplifyjs": "1.1.2", "jsforce": "1.4.1", "prettify": "r298", "es5-shim": "4.1.1", "loglevel": "1.2.0", "proj4js": "2.3.6", "feedback.js": "2012.10.17", "pusher-angular": "0.1.4", "wysihtml5": "0.3.0", "jquery-ui-bootstrap": "0.5pre", "jquery.activity-indicator": "1.0.0", "leaflet.fullscreen": "1.0.0", "jquery-gamequery": "0.7.0", "fallback": "1.0.5", "dropzone": "4.0.1", "roundabout": "2.4.2", "simplestatemanager": "2.2.5", "dojo": "1.10.4", "oj.AceEditor": "latest", "piwik": "2.8.0-rc2", "qwery": "4.0.0", "jquery.ui-contextmenu": "1.9.0", "jquery-localScroll": "1.4.0", "validate.js": "0.7.1", "angularFire": "0.5.0", "datejs": "1.0", "stylus": "0.32.1", "Fort.js": "1.0.0", "jquery-sparklines": "2.1.2", "jquery-footable": "0.1.0", "veinjs": "0.3", "eldarion-ajax": "0.12.0", "bootstrap-datepicker": "1.4.0", "epiceditor": "0.2.2", "operative": "0.4.4", "jquery.smartbanner": "1.0.0", "angular-google-maps": "2.1.0-X.10", "jquery.isotope": "2.2.0", "hammer.js": "2.0.4", "msl-client-browser": "1.0.6", "jquery-csv": "0.71", "chosen": "1.4.2", "mojio-js": "3.2.1", "jquery.formalize": "1.2", "Director": "1.2.8", "jsonld": "0.3.22", "jit": "2.0.2", "crel": "2.1.8", "jquery.socialshareprivacy": "1.6", "openlayers": "2.13.1", "react-slick": "0.4.1", "scriptaculous": "1.9.0", "equalize.js": "1.0.1", "xregexp": "2.0.0", "bignumber.js": "2.0.7", "rxjs-jquery": "1.1.6", "jquery-dateFormat": "1.0", "ember.js": "1.12.0-beta.3", "resumable.js": "1.0", "jeditable.js": "1.7.3", "Ladda": "0.9.8", "backbone.paginator": "0.154", "placeholder-shiv": "0.2", "jquery-infinitescroll": "2.0b2.120519", "skel-layers": "2.0.2", "html5media": "1.1.8", "shred": "1.1.0-alpha-06", "SoundJS": "0.6.0", "parallax": "1.1.1", "idbwrapper": "1.5.0", "angular-data": "1.5.3", "q.js": "2.0.3", "lz-string": "1.4.3", "headroom": "0.7.0", "knockback": "0.20.5", "aurora.js": "0.4.2", "selectivizr": "1.0.2", "github-org-members.js": "1.0.0", "jquery.pjax": "1.9.6", "stacktrace.js": "0.6.4", "persian.js": "0.3.0", "interact.js": "1.2.4", "jquery-image-upload": "1.0.0", "jquery-ui-map": "3.0-rc1", "probtn": "1.0.1", "analytics.js": "2.8.17", "bootstrap-datetimepicker": "4.7.14", "dustjs-helpers": "1.7.1", "jquery-bootgrid": "1.2.0-rc", "css3finalize": "4.1.0", "ng-token-auth": "0.0.25-beta1", "backbone-pageable": "1.4.8", "draggabilly": "1.2.3", "angular-ui-select": "0.11.2", "entypo": "2.0", "vega": "1.5.0", "jquery-countdown": "2.0.1", "legojs": "0.0.1", "numeric": "1.2.6", "highstock": "2.1.5", "markdown-it": "4.2.1", "jquery.gray": "1.3.3", "slidesjs": "3.0", "jquery-te": "1.4.0", "infinity": "0.2.2", "l20n": "1.0.2", "requirejs-mustache": "0.0.2", "humanize-plus": "1.5.0", "handlebars.js": "3.0.3", "firebug-lite": "1.4.0", "psd.js": "0.4.5", "intro.js": "1.0.0", "spectrum": "1.7.0", "jquery_lazyload": "1.9.5", "flexie": "1.0.3", "list.pagination.js": "0.1.1", "snap.js": "1.9.2", "sco.js": "1.1.0", "musicmetadata": "0.3.11", "backbone-localstorage.js": "1.1.16", "knockout-bootstrap": "0.2.1", "angular-gantt": "1.2.5", "outdated-browser": "1.1.0", "messenger": "1.4.0", "pagedown": "1.0", "jquery.rest": "1.0.2", "bootbox.js": "4.4.0", "cufon": "1.09i", "foundation": "5.5.2", "templatebinding": "0.3.4", "fast-json-patch": "0.5.2", "joopl": "2.3.0", "danialfarid-angular-file-upload": "4.1.3", "html5shiv": "r29", "bsjs": "0.3.0", "knockout-pre-rendered": "0.4.1", "blueimp-file-upload": "9.5.7", "neo-async": "1.0.1", "treesaver": "0.10.0", "angular-ui-date": "0.0.7", "topojson": "1.6.19", "melonjs": "1.0.1", "jStorage": "0.4.12", "humane-js": "3.0.6", "ember-data.js": "1.0.0-beta.16.1", "jszip": "2.5.0", "orb": "1.0.8", "gmaps.js": "0.4.12", "card": "0.0.2", "fotorama": "4.6.4", "label.css": "0.1.1", "ckeditor": "4.4.5", "sugar": "1.4.1", "openajax-hub": "2.0.7", "string.js": "3.1.1", "sylvester": "0.1.3", "angular-carousel": "0.3.10", "kendo-ui-core": "2014.1.416", "yui": "3.18.0", "backbone.wreqr": "1.3.2", "angular-hotkeys": "1.4.5", "elasticsearch": "4.0.2", "soundmanager2": "2.97a.20140901", "zeroclipboard": "2.2.0", "angular-retina": "0.3.1", "ionic": "1.0.0-rc.5", "twilio.js": "1.2.0", "jquery.spritely": "0.6.8", "jquery-scrollTo": "2.1.0", "trianglify": "0.2.1", "jquery.hashcash.io": "0.0.2", "alertify.js": "0.3.11", "jQuery-Validation-Engine": "2.6.4", "x-editable": "1.5.1", "video.js": "4.12.5", "angular-bindonce": "0.3.1", "jquery-resize": "1.1", "jquery.form": "3.51", "insightjs": "1.4.0", "jquery-jcrop": "0.9.12", "jsondiffpatch": "0.1.31", "pablo": "0.4.0", "datatables-tabletools": "2.1.5", "ember-charts": "0.4.0", "pegjs": "0.7.0", "backbone.validation": "0.11.4", "gremlins.js": "0.1.0", "jquery-replace-text": "1.1.0", "kube": "3.0.2", "underscore.string": "3.0.3", "jquery.matchHeight": "0.6.0", "moment.js": "2.10.2", "cldrjs": "0.4.1", "jquery.atmosphere": "2.1.2", "jquery-smart-web-app-banner": "1.4", "crypto-js": "3.1.2", "fixed-header-table": "1.3.0", "eddy": "0.7.0", "piecon": "0.2", "userinfo": "1.1.0", "6to5": "3.6.5", "seajs": "3.0.1", "basket.js": "0.5.2", "jquery-bootpag": "1.0.4", "mermaid": "0.4.0", "intercom.js": "0.1.4", "easyXDM": "2.4.18.25", "emblem": "0.4.0", "Sly": "1.2.1", "floatthead": "1.2.10", "lodash.js": "3.8.0", "jqPlot": "1.0.8", "simplecartjs": "3.0.5", "spectrum-i18n": "1.3.0", "maquette": "1.7.0", "zurb-ink": "1.0.5", "jquery.tipsy": "1.0.2", "rickshaw": "1.5.1", "matreshka": "1.0.5", "ractive": "0.7.3", "whereyat": "0.1.2", "waypoints": "2.0.5", "holder": "2.7.1", "jqplugin": "1.0.2", "numbro": "1.1.1", "jquery-form-serializer": "1.1.0", "jquery-history": "1.9", "PapaParse": "4.1.1", "font-awesome": "4.3.0", "doony": "2.1", "crossroads": "0.12.0", "jquery.SPServices": "2014.02", "js-url": "1.8.4", "architect": "0.1.0", "shepherd": "0.7.1", "FileSaver.js": "2014-11-29", "angular-ui-utils": "0.1.1", "numeral.js": "1.5.3", "qoopido.js": "3.6.0", "howler": "1.1.26", "ekko-lightbox": "3.3.0", "minicart": "3.0.6", "skycons": "1396634940", "Base64": "0.3.0", "elm-runtime": "0.8.0.3", "oj.mustache": "latest", "sevenSeg.js": "0.2.0", "alloy-ui": "1.0.1", "annyang": "1.6.0", "geojs": "0.4.2", "dollar.js": "1.1.0", "crossfilter": "1.3.11", "tagmanager": "3.0.0", "script.js": "2.5.7", "angular-motion": "0.3.4", "sass.js": "0.8.1", "audiosynth": "1.0.0", "noti.js": "1.0.2", "onsen": "1.2.0-beta", "tinymce": "4.1.9", "chainvas": "2.1", "polymaps": "2.5.1", "zxcvbn": "1.0", "strophe.js": "1.1.3", "cropper": "0.9.1", "jquery.bootstrapvalidator": "0.5.3", "paymentfont": "1.1.2", "zepto": "1.1.6", "jquery.serialScroll": "1.3.0", "immstruct": "1.4.0", "bower-angular-translate-loader-static-files": "2.7.0", "knockout.mapping": "2.4.1", "PullToRefresh": "0.1.1", "jquery.pep": "0.4.0", "viewer.js": "0.10.6", "livescript": "1.3.1", "bootstrap-social": "4.9.0", "jquery.colorbox": "1.4.33", "hinclude": "0.9.5", "highlight.js": "8.5", "angular-translate-interpolation-messageformat": "2.7.0", "jquery-sheetrock": "1.0.0", "require-css": "0.1.8", "js-data-localforage": "2.0.0-beta.1", "valjs": "1.0", "jquery-cookie": "1.4.1", "jquery-treegrid": "0.2.0", "bluebird": "2.9.25", "jasmine-ajax": "3.1.1", "cc-icons": "1.2.1", "select2-bootstrap-css": "1.4.6", "bootstrap-select": "2.0.0-beta1", "bacon.js": "0.7.53", "rimg": "1.6.0", "gridstack.js": "0.2.2", "toxiclibsjs": "0.1.3", "embedly-jquery": "3.1.1", "FlipDiv": "1.6.0", "crafty": "0.5.4", "leaflet": "0.7.3", "FitText.js": "1.1", "fitvids": "1.1.0", "absurd": "0.3.158", "playlyfe-js-sdk": "0.9.0", "mediaelement": "2.16.4", "animate.css": "3.2.6", "log4javascript": "1.4.9", "dot": "1.0.3", "validator": "3.12.0", "mocha": "2.2.4", "prototype": "1.7.2", "1140": "2.0", "r2d3": "0.2.0", "string_score": "0.1.22", "jqModal": "r14", "Han": "3.2.1", "leaflet.markercluster": "0.4.0", "allmighty-autocomplete": "1.0.140706", "joyride": "2.1.0", "angular-loading-bar": "0.7.1", "cascade-framework": "1.5.0", "colors": "1.0", "backbone.collectionView": "0.11.5", "iScroll": "5.1.1", "social-likes": "3.0.14", "dd_belatedpng": "0.0.8", "punycode": "1.3.2", "tooltipster": "3.0.5", "octicons": "2.2.2", "d3": "3.5.5", "sanitize.css": "2.0.0", "imgareaselect": "0.9.10", "meny": "1.4.0", "lettering.js": "0.6.1", "kartograph-js": "0.8.7", "clappr": "0.0.115", "catiline": "2.9.3", "gulp": "3.8.5", "dancer.js": "0.4.0", "bootstrap-material-design": "0.3.0", "backgrid.js": "0.3.5", "kiss.animate": "0.1.2", "backbone.syphon": "0.4.1", "backbone.ribs": "0.2.2", "jquery.waitforimages": "1.5.0", "jquery": "2.1.4", "clank": "0.3.6", "SVG-Morpheus": "0.1.8", "jquery.lazyload": "1.9.1", "tinyscrollbar": "1.81", "angular-image-spinner": "0.1.5", "oj.TwitterButton": "latest", "dc": "2.0.0-beta.9", "jmpress": "0.4.5", "motion.js": "0.3.0", "bean": "1.0.15", "ICanHaz.js": "0.10.3", "jquery-timeago": "1.4.1", "angular-ui-sortable": "0.13.3", "angular-busy": "4.1.3", "angular-translate-loader-url": "2.7.0", "jquery-backstretch": "2.0.4", "fpsmeter": "0.3.1", "Snowstorm": "20131208", "ixjs": "1.0.6", "tether-tooltip": "0.2.6", "ie8": "0.2.3", "backbone.radio": "0.9.0", "kibo": "1.1.0", "moment-range": "1.0.9", "brain": "0.6.3", "less.js": "2.5.0", "s3colors": "1.0", "jquery.mask": "0.9.0", "fullPage.js": "2.6.5", "react-foundation-apps": "0.6.0", "ammaps": "3.13.0", "blueimp-md5": "1.1.0", "ng-dialog": "0.4.0", "webkit.js": "0.1.0", "spin.js": "2.0.1", "jshint": "2.7.0", "authy-forms.css": "2.2", "angular-css": "1.0.7", "speakingurl": "2.0.0", "datatables": "1.10.7", "github-fork-ribbon-css": "0.1.1", "fullcalendar": "2.3.1", "jade": "1.9.2", "showdown": "0.5.0", "froala-editor": "1.2.6", "require-i18n": "2.0.4", "tether": "0.7.1", "jquery-toggles": "2.0.4", "device.js": "0.2.7", "socket.io": "1.3.5", "topcoat-icons": "0.2.0", "geocomplete": "1.4", "componentjs": "1.2.4", "knockout-sortable": "0.11.0", "swagger-ui": "2.1.8-M1", "JQuery-Snowfall": "1.7.4", "jquery.finderselect": "0.6.0", "dom4": "1.4.3", "ember-data-django-rest-adapter": "0.13.1", "oj.VimeoVideo": "latest", "TinyNav.js": "1.2.0", "phaser": "2.3.0", "backbone.js": "1.1.2", "jqlouds": "0.2.3", "d3plus": "1.7.1", "wow": "1.1.2", "ModelCore": "1.0", "impress.js": "0.5.3", "jquery.payment": "1.2.3", "jquery.serializeJSON": "1.2.0", "jquery-browser": "0.0.7", "DinaKit": "1.2", "yepnope": "1.5.4", "ladda-bootstrap": "0.9.4", "superfish": "1.7.4", "angular-translate-storage-local": "2.7.0", "jquery.googlemap": "1.4.2", "raven.js": "1.1.11", "coordinates-picker": "1.0.0", "magnific-popup.js": "1.0.0", "angular-pusher": "0.0.14", "h5Validate": "0.8.4", "buckets": "1.90.0", "yasr": "2.5.3", "jquery-validate": "1.13.1", "boexfi": "1.0.0", "diff_match_patch": "20121119", "jo": "0.4.1", "amcharts": "3.13.0", "kwargsjs": "1.0.1", "ng-flow": "2.6.1", "jquery.postcodify": "2.5.0", "use.js": "0.4.0", "Swiper": "3.0.7", "jqcloud": "1.0.4", "jquery-mousewheel": "3.1.12", "jquery-json": "2.5.1", "vue": "0.11.9", "turbolinks": "1.3.0", "PreloadJS": "0.6.0", "cutjs": "0.4.14", "aurora.js-alac": "0.1.0", "opal": "0.3.43", "commandz": "0.1.2", "gsap": "latest", "pace": "1.0.2", "UAParser.js": "0.7.7", "twitterlib.js": "1.0.8", "jquery-handsontable": "0.10.2", "then-request": "2.1.1", "angular-filter": "0.5.4", "restangular": "1.5.1", "es6-shim": "0.31.0", "angular-translate-loader-partial": "2.7.0", "allow-me": "0.1.1", "mindb": "0.0.4", "peerjs": "0.3.14", "WebRupee": "2.0", "detectizr": "1.5.0", "co": "4.1.0", "datatables-colvis": "1.1.0", "sjcl": "1.0.0", "oj.markdown": "latest", "ninjaui": "1.0.1", "ajile": "2.1.7", "reconnecting-websocket": "1.0.0", "springy": "2.5.0", "toast-css": "1.0.0", "toastr.js": "latest", "file-uploader": "3.7.0", "twitter-bootstrap-wizard": "1.2", "topcoat": "0.8.0", "jquery.notification": "1.0.2", "flocks.js": "1.6.1", "jcalculator": "1403955268", "atmosphere": "2.1.2", "conditionizr.js": "4.1.0", "angular-local-storage": "0.1.5", "platform": "1.3.0", "flexslider": "2.3.0", "jquery-domPath": "1.0.0", "html5-history-api": "4.0.2", "jquery.shapeshift": "2.0", "react-cookie": "0.1.8", "angular-translate": "2.7.0", "jquery-overscroll": "1.7.7", "jplist": "5.1.38", "queue-async": "1.0.7", "jquery-jkit": "1.1.8", "angular-mixpanel": "1.1.0", "tablesort": "3.0.2", "bootstrap-hover-dropdown": "2.0.10", "mixitup": "1.5.6", "CoolQueue.io": "1.0.0", "xlsx": "0.8.0", "algoliasearch": "3.2.2", "jquery.liveurl": "1.2.2", "flight": "1.1.4", "jquery.downCount": "1.0.0", "requirejs-async": "0.1.1", "ng-slider": "2.2.6", "mootools": "1.5.1", "requirejs-plugins": "1.0.3", "overthrow": "0.7.0", "gas": "1.11.0", "pie": "1.0beta5", "jquery.poptrox": "2.5.1", "stomp.js": "2.3.3", "cannon.js": "0.6.2", "enquire.js": "2.1.2", "min.js": "0.2.3", "c3": "0.4.10-rc5", "foggy": "1.02", "deb.js": "0.0.1", "scrollify": "0.1.6", "amstockchart": "3.13.0", "jquery.inputmask": "3.1.62", "jquery.address": "1.6", "sortable": "0.6.0", "leapjs": "0.6.1", "snabbt.js": "0.5.2", "uikit": "2.20.3", "tinycolor": "1.1.2", "audio5js": "0.1.10", "SyntaxHighlighter": "3.0.83", "jScrollPane": "2.0.14", "authy-form-helpers": "2.3", "hellojs": "1.5.1", "ratchet": "2.0.2", "backbone.stickit": "0.8.0", "caiuss": "1.0.2", "bower-angular-translate-loader-partial": "2.7.0", "scrollReveal.js": "0.1.2", "Leaflet.awesome-markers": "2.0.2", "jplayer": "2.9.2", "aurora.js-flac": "0.2.1", "requirejs-handlebars": "0.0.2", "bootswatch": "3.3.4", "Kalendae": "0.4.1", "backbone-tastypie": "0.2", "geo-location-javascript": "0.4.8", "jquery-layout": "1.4.3", "jquery-tagsinput": "1.3.3", "jquery.cycle2": "20140415", "taffydb": "2.7.2", "aurora.js-aac": "0.1.0", "ember-simple-auth": "0.8.0-beta.2", "coin-slider": "1.0.0", "jquery.swipebox": "1.3.0.2", "js-data-firebase": "2.0.0-beta.1", "websqltracer": "1.0.2", "page.js": "1.6.3", "bucky": "0.2.6", "jquery.fileDownload": "1.4.2", "KaTeX": "0.3.0", "SlickNav": "1.0.3", "pizza": "0.2.1", "angulartics": "0.17.2", "swipe": "2.0", "store.js": "1.3.14", "leaflet-providers": "1.0.29", "backbone-associations": "0.6.2", "eventmaster": "2.0.0", "FuncUnit": "2.0.4", "jq-console": "2.7.7", "meyer-reset": "2.0", "matter-js": "0.8.0-alpha", "progress.js": "0.1.0", "angular-ui-bootstrap": "0.13.0", "jquery-scrolldepth": "0.6", "epoch": "0.6.0", "ext-core": "3.1.0", "unveil": "1.3.0", "swig": "1.4.2", "ng-clip": "0.2.6", "jquery.maskedinput": "1.3.1", "Sortable": "1.2.0", "django.js": "0.8.1", "jquery.tablesorter": "2.21.5", "rainbow": "1.2.0", "buzz": "1.1.10", "backbone.routefilter": "0.2.0", "playlyfe-odysseus": "0.5.6", "sbt": "1.1.3.20150220", "labjs": "2.0.3", "web-starter-kit": "0.2.0-beta", "sopa": "1.0", "portal": "1.1.1", "vault.js": "0.1.9", "js-yaml": "3.3.0", "nwmatcher": "1.2.5", "evil.js": "42", "aws-sdk": "2.1.26", "codemirror": "5.2.0", "jstimezonedetect": "1.0.4", "jquery.simpleWeather": "3.0.2", "dinqyjs": "1.1.0", "Cookies.js": "1.2.1", "jquery.mb.YTPlayer": "2.8.5", "ng-grid": "2.0.11", "visibility.js": "1.2.1", "angular-route-segment": "1.4.0", "slick-carousel": "1.5.2", "tabletop.js": "1.3.5", "angularjs-toaster": "0.4.13", "highcharts": "4.1.5", "react-router": "0.13.2", "rome": "2.1.17", "select2": "4.0.0-rc.2", "stampit": "0.7.1", "jquery-json-editor": "1.1.0", "skrollr": "0.6.29", "fuelux": "3.7.1", "coffee-script": "1.9.2", "ember-auth": "9.0.7", "jquery.pin": "1.0.1", "tinycon": "0.5", "jquery.formset": "1.2", "when": "2.7.1", "reveal.js": "3.0.0", "html2canvas": "0.5.0-alpha2", "jquery-form-validator": "2.2.1", "free-jqgrid": "4.8.0", "foundation-essential": "5.5.2", "noUiSlider": "6.2.0", "angular-scroll": "0.7.0", "highmaps": "1.1.5", "domplotter": "1.3.1", "web-socket-js": "1.0.0", "dropbox.js": "0.10.3", "evil-icons": "1.7.6", "jquery.touchswipe": "1.6.4", "jquery-mobile": "1.4.5", "unsemantic": "0", "graphael": "0.5.1", "pouchdb": "3.4.0", "pickadate.js": "3.5.6", "beeplay": "0.0.5", "ng-context-menu": "v1.0.1", "ouibounce": "0.0.11", "minitranslate": "1.2.0", "myscript": "1.0.5", "jquery.selection": "1.0.1", "jointjs": "0.9.0", "featherlight": "1.2.3", "leaflet.draw": "0.2.3", "placeholders": "3.0.2", "aurora.js-mp3": "0.1.0", "jquery-color": "2.1.2", "authy-forms.js": "2.2", "anchor-js": "0.4.0", "angular-ui-calendar": "1.0.0", "jquery-placeholder": "2.0.8", "vis": "3.12.0", "medium-editor-custom-html": "1.1.0", "gist-embed": "2.1", "owl-carousel": "1.32", "set-iframe-height": "1.1.5", "underscore-contrib": "0.3.0", "scrollpoints": "0.2.0", "batman.js": "0.16.0", "subkit": "1.1.22", "lrsjng.jquery-qrcode": "0.11.0", "jquery-powertip": "1.2.0", "angular-vertxbus": "2.0.0-beta.6", "augment.js": "1.0.0", "svg.js": "2.0.0-rc.1", "nanobar": "0.2.1", "bla": "1.4.0", "pixi.js": "3.0.2", "interpolate.js": "1.1.0", "rainyday.js": "0.1.2", "chardin.js": "0.1.3", "jsface": "2.3.0", "angularSubkit": "1.0.3", "uvCharts": "1.0.0", "reqwest": "1.1.5", "qooxdoo": "4.1", "rxjs": "2.5.2", "jquery.tocify": "1.9.0", "async": "1.22", "jquery-easing": "1.3", "d3-geo-projection": "0.2.9", "spinejs": "1.2.0", "knockback-core-stack": "0.17.2", "fancybox": "2.1.5", "fingerprintjs": "v0.5.1", "p2.js": "0.6.1", "classlist": "2014.01.31", "modernizr": "2010.07.06dev", "angular-material": "0.9.0-rc3", "zclip": "1.1.2", "detect_swipe": "2.1.1", "three.js": "r71", "jQuery-slimScroll": "1.3.3", "jquery.lazyloadxt": "1.0.5", "davis.js": "0.9.5", "jquery-parallax": "1.1.3", "ng-csv": "0.3.3", "angular-poller": "0.3.2", "kiwi": "0.2.1", "typeahead.js": "0.10.5", "mobile-detect": "1.0.0", "shaka-player": "1.3.0", "opal-parser": "0.3.43", "malihu-custom-scrollbar-plugin": "3.0.8", "imagine.js": "0.1.0", "webshim": "1.15.7", "mousetrap": "1.4.6", "jquery-noty": "2.3.5", "jquery.qrcode": "1.0", "jquery.turbolinks": "2.0.2", "lightbox2": "2.7.1", "backbone.projections": "1.0.0", "angular-translate-handler-log": "2.7.0", "angularLocalStorage": "0.3.0", "tablefilter": "2.5.0", "jquery.customSelect": "0.5.1", "jquery.age": "1.2.4", "Flowtype.js": "1.1.0", "require-domReady": "2.0.1", "jquery-one-page-nav": "3.0.0", "svg.pan-zoom.js": "1.0.1", "json-mask": "0.1.1-alpha", "clientside-haml-js": "5.4", "AniJS": "0.9.3", "backbone-forms": "0.14.0", "ResponsiveSlides.js": "1.53", "jquery-scrollpanel": "0.5.0", "timelinejs": "2.35.6", "qtip2": "2.2.1", "twitter-bootstrap": "3.3.4", "ember-dialog": "1.2.5", "jquery-serialize-object": "2.0.0", "noisy": "1.2", "react": "0.13.2", "bootstrap-markdown": "2.8.0", "flickity": "1.0.2", "oj": "latest", "ace": "1.1.9", "balance-text": "1.3.0", "xls": "0.7.5", "nicescroll": "3.6.0", "oz.js": "2.5.1", "jsxgraph": "0.99.3", "jquery.superlabels": "2.0.3", "anima": "0.4.0", "prefixfree": "1.0.7", "bootstrap-tour": "0.10.1", "documentup": "latest.min.js", "dygraph": "1.2", "jquery-textext": "1.3.0", "oj.JSFiddle": "latest", "bootcards": "1.1.2", "helium-css": "1.1", "pym": "0.4.3", "dat-gui": "0.5", "anythingslider": "1.9.1", "bootstrap-rtl": "3.2.0-rc2", "handsontable": "0.15.0-beta2", "ionicons": "1.5.2", "rangeslider.js": "1.2.1", "jssip": "0.5.0", "angular-translate-loader-static-files": "2.7.0", "geoext": "1.1", "bootstrap-switch": "3.3.2", "polyglot": "2.2.0", "mini-meteor": "1.0.1", "bower-angular-translate-loader-url": "2.7.0", "require-jquery": "0.25.0", "custom-elements-builder": "0.3.4", "css-spinning-spinners": "1.1.0", "jquery-contextmenu": "1.6.5", "ember-i18n": "3.0.0-beta.2", "geojson2svg": "1.0.0", "Uniform.js": "2.1.2", "yasgui": "1.1.4", "jsoneditor": "4.1.3", "backbone.obscura": "0.1.6", "skel": "2.2.1", "jquery-ui-timepicker-addon": "1.4.5", "livestamp": "1.1.2", "markdown.js": "0.6.0-beta1", "requirejs-tpl": "0.0.2", "headjs": "1.0.3", "jquery-maskmoney": "3.0.2", "autosize.js": "1.18.18", "jquery-ajaxtransport-xdomainrequest": "1.0.3", "can.js": "1.1.7", "echarts": "2.2.2", "960gs": "0", "jquery.selectboxit": "3.8.0", "sizzle": "2.2.0", "keymage": "1.0.1", "sprite-js": "0.1.0", "side-comments": "0.0.1", "emojione": "1.4.0", "angular-ui": "0.4.0", "dragonbones": "2.4.1", "barman": "0.4.2", "blueimp-gallery": "2.15.2", "breezejs": "1.5.3", "respond.js": "1.4.2", "jQuery.dotdotdot": "1.7.2", "api-check": "7.2.2", "summernote": "0.6.6", "angular-smart-table": "2.0.2", "line-chart": "1.1.4", "semantic-ui": "1.12.2", "canvasjs": "1.4.1", "two.js": "0.4.0", "bootstrap-growl": "1.0.6", "jquery.fancytree": "2.9.0", "require-cs": "0.5.0", "jqueryui": "1.11.4", "lazyload": "2.0.3", "path.js": "0.8.4", "jquery.scregal": "1.3", "signet": "0.4.4", "fatcow-icons": "20130425", "chaplin": "0.11.3", "salesforce-canvas": "27.0", "mithril": "0.2.0", "backbone.marionette": "2.4.1", "iCheck": "1.0.1", "chai": "2.3.0", "kerning.js": "0.2", "savvior": "0.5.0", "hydra.js": "3.9.12", "oppia": "0.0.1", "hover.css": "2.0.2", "jquery.percentageloader": "0.1.0", "gumby": "2.6.0", "angular-wizard": "0.4.0", "flowplayer": "5.4.6", "lodash-compat": "3.8.0", "ink": "3.1.7", "hashgrid": "6", "curl": "0.7.3", "flot": "0.8.3", "jquery.nicescroll": "3.6.0", "repo.js": "5c0eae0f1b", "pusher": "2.2.4", "jquery-impromptu": "5.2.3", "riot": "2.0.15", "jquery-url-parser": "2.3.1", "paper.js": "0.22", "remoteStorage": "0.8.0", "jquery-jgrowl": "1.4.2", "load.js": "1316434407", "javascript-state-machine": "2.0.0", "jquery.imagesloaded": "3.1.8", "jQuery-Geolocation": "1.0.50", "jquery.photocols": "1.0.3", "pnotify": "2.0.0", "nanogallery": "5.6.0", "webcomponentsjs": "0.6.1", "tinysort": "2.2.2", "depot": "0.1.6", "instantclick": "3.0.1", "angular-cache": "4.2.0", "angular-i18n": "1.2.15", "jspdf": "1.0.272", "yasqe": "2.3.9", "chroma-js": "0.7.2", "simplemodal": "1.4.4", "github-repo-widget": "e23d85ab8f", "dustjs-linkedin": "2.7.1", "confidencejs": "1.2.0", "cryptico": "0.0.1343522940", "gillie": "0.2.1", "nvd3": "1.8.1-alpha", "kineticjs": "5.2.0", "jquery-throttle-debounce": "1.1", "chance": "0.5.6", "retina.js": "1.3.0", "preconditions": "5.3.0", "EventEmitter": "4.2.11", "postal.js": "1.0.3", "wuzzle": "1.1.0", "jquery.is.js": "0.2.1", "backbone.fetch-cache": "1.1.2", "extjs": "4.2.1", "thorax": "2.2.1", "vertx": "2.0.0", "bootstrap-formhelpers": "2.3.0", "ScrollMagic": "2.0.5", "zocial": "0", "js-data": "2.0.0-beta.4", "stats.js": "r11", "raphael": "2.1.2", "backbone.babysitter": "0.1.6", "i18next": "1.6.3", "jquery-tubeplayer": "1.1.6", "jquery-visibility": "1.0.11", "hogan.js": "3.0.2", "ember-computed-reverse": "0.1.0", "machina.js": "1.0.0-2", "js-signals": "1.0.0", "jquery-migrate": "1.2.1", "winjs": "4.0.0-preview", "emojify.js": "0.9.5", "tabcomplete": "1.4.0"}